{
  "tickers": {
    "IONQ": {
      "as_of": "2026-07-09",
      "close": 44.77,
      "atr14": 4.481,
      "rsi14": 35.9,
      "sma20": 53.12,
      "sma50": 55.09,
      "sma200": 49.19,
      "high52w": 82.09,
      "levels": {
        "screen": "no clean setup",
        "entry_low": 42.53,
        "entry_high": 47.01,
        "stop": 38.05,
        "tp": 68.79,
        "tp_source": "analyst PT",
        "upside": 53.7
      },
      "strategies": {
        "donchian_20_10": {
          "state": "FLAT",
          "last_flip_date": "2026-06-25",
          "entry_price_if_long": null,
          "unrealized_pct": null,
          "trigger_detail": "trigger \u2191 $63.95 (+42.8%)"
        },
        "sma_20_50": {
          "state": "FLAT",
          "last_flip_date": "2026-07-07",
          "entry_price_if_long": null,
          "unrealized_pct": null,
          "trigger_detail": "SMA20 $53.12 \u00b7 SMA50 $55.09 \u00b7 gap -3.6%"
        },
        "trend_filter": {
          "state": "FLAT",
          "last_flip_date": "2026-07-02",
          "entry_price_if_long": null,
          "unrealized_pct": null,
          "trigger_detail": "SMA20/50/200 $53.12/$55.09/$49.19 \u00b7 regime \u2717 below 200"
        },
        "macd": {
          "state": "FLAT",
          "last_flip_date": "2026-06-05",
          "entry_price_if_long": null,
          "unrealized_pct": null,
          "trigger_detail": "MACD -2.954 \u00b7 signal -1.700 \u00b7 gap -1.255"
        },
        "atr_trail": {
          "state": "FLAT",
          "last_flip_date": "2026-07-07",
          "entry_price_if_long": null,
          "unrealized_pct": null,
          "trigger_detail": "SMA20 $53.12 \u00b7 SMA50 $55.09 \u00b7 gap -3.6%"
        }
      },
      "fundamentals": {
        "market_cap": 16711296000,
        "fifty_two_high": 84.64,
        "fifty_two_low": 25.89,
        "beta": 3.23,
        "revenue_ttm": 187118000,
        "cash": 2033469952,
        "debt": 30443000,
        "ps_ratio": 89.30886,
        "short_pct_float": 0.136,
        "rec_key": "strong_buy",
        "rec_label": "Strong Buy",
        "analyst_count": 13,
        "target_mean": 68.79077,
        "target_high": 100.0,
        "target_low": 44.78
      }
    },
    "ONDS": {
      "as_of": "2026-07-09",
      "close": 7.65,
      "atr14": 0.726,
      "rsi14": 39.5,
      "sma20": 8.41,
      "sma50": 9.57,
      "sma200": 9.44,
      "high52w": 14.01,
      "levels": {
        "screen": "no clean setup",
        "entry_low": 7.29,
        "entry_high": 8.01,
        "stop": 6.56,
        "tp": 19.81,
        "tp_source": "analyst PT",
        "upside": 159.0
      },
      "strategies": {
        "donchian_20_10": {
          "state": "FLAT",
          "last_flip_date": "2026-06-22",
          "entry_price_if_long": null,
          "unrealized_pct": null,
          "trigger_detail": "trigger \u2191 $10.41 (+36.1%)"
        },
        "sma_20_50": {
          "state": "FLAT",
          "last_flip_date": "2026-06-26",
          "entry_price_if_long": null,
          "unrealized_pct": null,
          "trigger_detail": "SMA20 $8.41 \u00b7 SMA50 $9.57 \u00b7 gap -12.1%"
        },
        "trend_filter": {
          "state": "FLAT",
          "last_flip_date": "2026-06-16",
          "entry_price_if_long": null,
          "unrealized_pct": null,
          "trigger_detail": "SMA20/50/200 $8.41/$9.57/$9.44 \u00b7 regime \u2717 below 200"
        },
        "macd": {
          "state": "FLAT",
          "last_flip_date": "2026-06-08",
          "entry_price_if_long": null,
          "unrealized_pct": null,
          "trigger_detail": "MACD -0.695 \u00b7 signal -0.650 \u00b7 gap -0.045"
        },
        "atr_trail": {
          "state": "FLAT",
          "last_flip_date": "2026-06-26",
          "entry_price_if_long": null,
          "unrealized_pct": null,
          "trigger_detail": "SMA20 $8.41 \u00b7 SMA50 $9.57 \u00b7 gap -12.1%"
        }
      },
      "fundamentals": {
        "market_cap": 4359265280,
        "fifty_two_high": 15.28,
        "fifty_two_low": 1.78,
        "beta": 2.691,
        "revenue_ttm": 96605000,
        "cash": 1473844992,
        "debt": 7865000,
        "ps_ratio": 45.124634,
        "short_pct_float": 0.32419997,
        "rec_key": "strong_buy",
        "rec_label": "Strong Buy",
        "analyst_count": 8,
        "target_mean": 19.8125,
        "target_high": 25.0,
        "target_low": 16.0
      }
    },
    "VRT": {
      "as_of": "2026-07-09",
      "close": 323.92,
      "atr14": 22.452,
      "rsi14": 52.1,
      "sma20": 314.27,
      "sma50": 324.42,
      "sma200": 235.93,
      "high52w": 376.15,
      "levels": {
        "screen": "uptrend cooling",
        "entry_low": 321.18,
        "entry_high": 327.66,
        "stop": 231.21,
        "tp": 377.0,
        "tp_source": "analyst PT",
        "upside": 16.4
      },
      "strategies": {
        "donchian_20_10": {
          "state": "LONG",
          "last_flip_date": "2026-06-22",
          "entry_price_if_long": 337.96,
          "unrealized_pct": -4.15,
          "trigger_detail": "exit \u2193 $287.11 (-11.4%)"
        },
        "sma_20_50": {
          "state": "FLAT",
          "last_flip_date": "2026-06-15",
          "entry_price_if_long": null,
          "unrealized_pct": null,
          "trigger_detail": "SMA20 $314.27 \u00b7 SMA50 $324.42 \u00b7 gap -3.1%"
        },
        "trend_filter": {
          "state": "FLAT",
          "last_flip_date": "2026-06-15",
          "entry_price_if_long": null,
          "unrealized_pct": null,
          "trigger_detail": "SMA20/50/200 $314.27/$324.42/$235.93 \u00b7 regime \u2713 above 200"
        },
        "macd": {
          "state": "LONG",
          "last_flip_date": "2026-07-09",
          "entry_price_if_long": 333.55,
          "unrealized_pct": -2.89,
          "trigger_detail": "MACD -0.588 \u00b7 signal -1.105 \u00b7 gap +0.517"
        },
        "atr_trail": {
          "state": "FLAT",
          "last_flip_date": "2026-06-15",
          "entry_price_if_long": null,
          "unrealized_pct": null,
          "trigger_detail": "SMA20 $314.27 \u00b7 SMA50 $324.42 \u00b7 gap -3.1%"
        }
      },
      "fundamentals": {
        "market_cap": 124420530176,
        "fifty_two_high": 379.935,
        "fifty_two_low": 110.06,
        "beta": 2.029,
        "revenue_ttm": 10843400192,
        "cash": 2500499968,
        "debt": 3264900096,
        "ps_ratio": 11.47431,
        "short_pct_float": 0.039100002,
        "rec_key": "strong_buy",
        "rec_label": "Strong Buy",
        "analyst_count": 25,
        "target_mean": 377.0,
        "target_high": 500.0,
        "target_low": 236.0
      }
    },
    "GENB": {
      "as_of": "2026-07-09",
      "close": 15.72,
      "atr14": 1.144,
      "rsi14": 53.4,
      "sma20": 15.33,
      "sma50": 14.36,
      "sma200": null,
      "high52w": 17.41,
      "levels": {
        "screen": "no clean setup",
        "entry_low": 15.15,
        "entry_high": 16.29,
        "stop": 14.0,
        "tp": 25.4,
        "tp_source": "analyst PT",
        "upside": 61.6
      },
      "strategies": {
        "donchian_20_10": {
          "state": "LONG",
          "last_flip_date": "2026-06-22",
          "entry_price_if_long": 15.44,
          "unrealized_pct": 1.81,
          "trigger_detail": "exit \u2193 $15.11 (-3.9%)"
        },
        "sma_20_50": {
          "state": "LONG",
          "last_flip_date": "2026-06-24",
          "entry_price_if_long": 16.36,
          "unrealized_pct": -3.91,
          "trigger_detail": "SMA20 $15.33 \u00b7 SMA50 $14.36 \u00b7 gap +6.7%"
        },
        "trend_filter": {
          "state": "FLAT",
          "last_flip_date": "2026-02-27",
          "entry_price_if_long": null,
          "unrealized_pct": null,
          "trigger_detail": ""
        },
        "macd": {
          "state": "FLAT",
          "last_flip_date": "2026-07-09",
          "entry_price_if_long": null,
          "unrealized_pct": null,
          "trigger_detail": "MACD +0.730 \u00b7 signal +0.765 \u00b7 gap -0.036"
        },
        "atr_trail": {
          "state": "LONG",
          "last_flip_date": "2026-06-24",
          "entry_price_if_long": 16.36,
          "unrealized_pct": -3.91,
          "trigger_detail": "HWM $17.41 \u00b7 trailing stop $13.98 (-11.1%)"
        }
      },
      "fundamentals": {
        "market_cap": 2015185792,
        "fifty_two_high": 18.18,
        "fifty_two_low": 11.0,
        "beta": null,
        "revenue_ttm": 30299000,
        "cash": 516640992,
        "debt": 65570000,
        "ps_ratio": 66.50998,
        "short_pct_float": 0.060900003,
        "rec_key": "none",
        "rec_label": "None",
        "analyst_count": 5,
        "target_mean": 25.4,
        "target_high": 30.0,
        "target_low": 22.0
      }
    },
    "NOK": {
      "as_of": "2026-07-09",
      "close": 12.9,
      "atr14": 0.868,
      "rsi14": 46.7,
      "sma20": 13.39,
      "sma50": 13.9,
      "sma200": 8.75,
      "high52w": 16.85,
      "levels": {
        "screen": "uptrend cooling",
        "entry_low": 13.76,
        "entry_high": 14.04,
        "stop": 8.57,
        "tp": 15.16,
        "tp_source": "analyst PT",
        "upside": 17.5
      },
      "strategies": {
        "donchian_20_10": {
          "state": "FLAT",
          "last_flip_date": "2026-06-09",
          "entry_price_if_long": null,
          "unrealized_pct": null,
          "trigger_detail": "trigger \u2191 $15.07 (+16.8%)"
        },
        "sma_20_50": {
          "state": "FLAT",
          "last_flip_date": "2026-07-06",
          "entry_price_if_long": null,
          "unrealized_pct": null,
          "trigger_detail": "SMA20 $13.39 \u00b7 SMA50 $13.90 \u00b7 gap -3.7%"
        },
        "trend_filter": {
          "state": "FLAT",
          "last_flip_date": "2026-07-06",
          "entry_price_if_long": null,
          "unrealized_pct": null,
          "trigger_detail": "SMA20/50/200 $13.39/$13.90/$8.75 \u00b7 regime \u2713 above 200"
        },
        "macd": {
          "state": "FLAT",
          "last_flip_date": "2026-06-05",
          "entry_price_if_long": null,
          "unrealized_pct": null,
          "trigger_detail": "MACD -0.477 \u00b7 signal -0.308 \u00b7 gap -0.169"
        },
        "atr_trail": {
          "state": "FLAT",
          "last_flip_date": "2026-07-02",
          "entry_price_if_long": null,
          "unrealized_pct": null,
          "trigger_detail": "SMA20 $13.39 \u00b7 SMA50 $13.90 \u00b7 gap -3.7%"
        }
      },
      "fundamentals": {
        "market_cap": 72014692352,
        "fifty_two_high": 17.45,
        "fifty_two_low": 4.0,
        "beta": 0.794,
        "revenue_ttm": 19996000256,
        "cash": 5830000128,
        "debt": 3324999936,
        "ps_ratio": 3.601455,
        "short_pct_float": 0.0115,
        "rec_key": "buy",
        "rec_label": "Buy",
        "analyst_count": 9,
        "target_mean": 15.15556,
        "target_high": 21.0,
        "target_low": 8.5
      }
    }
  }
}